Metadata-Version: 2.1
Name: matplotlii
Version: 0.1
Summary: Plotting Library 
Author-email: dongareashish602@gmail.com
